{
  "generatedAt": "2026-04-30T10:45:17.329Z",
  "totalRoutes": 700,
  "byLayout": {
    "Public Marketing": 106,
    "Public": 468,
    "Dashboard": 15,
    "Institution/Bank": 4,
    "Merchant": 4,
    "Admin": 1,
    "Business PWA": 4,
    "Customer PWA": 2,
    "Developer": 2,
    "Banking App": 2
  },
  "routes": {
    "Public Marketing": [
      "*",
      "/",
      "/about",
      "/analytics",
      "/api-catalog",
      "/api/error-codes",
      "/api/idempotency",
      "/api/rate-limits",
      "/api/sandbox-testing",
      "/api/security",
      "/api/versioning",
      "/api/webhooks",
      "/apps",
      "/architecture",
      "/architecture/disaster-recovery",
      "/architecture/fraud-engine",
      "/architecture/infrastructure",
      "/architecture/ledger-system",
      "/architecture/reconciliation-framework",
      "/architecture/risk-scoring-model",
      "/architecture/settlement-engine",
      "/aup",
      "/bank-integration-guide",
      "/business-accounts",
      "/certification/a-grade-status",
      "/compliance",
      "/compliance/aml-policy",
      "/compliance/kyc-framework",
      "/compliance/risk-monitoring",
      "/consents",
      "/contact",
      "/cookies",
      "/crediq/onboarding",
      "/crediq/settings",
      "/credit-api-docs",
      "/credit-scores-info",
      "/data-protection",
      "/documentation",
      "/expansion/:country",
      "/faq",
      "/for-developers",
      "/for-merchants",
      "/fund-account",
      "/guides/aisp",
      "/guides/certificates",
      "/guides/pisp",
      "/guides/security",
      "/guides/webhooks",
      "/help-centre",
      "/integration-workflow",
      "/integrations",
      "/integrations/bubble",
      "/integrations/make",
      "/integrations/retool",
      "/integrations/woocommerce-docs",
      "/integrations/woocommerce-merchant-register",
      "/integrations/woocommerce-plugin-code",
      "/integrations/zapier",
      "/investors/compliance-status",
      "/investors/infrastructure-maturity",
      "/investors/risk-disclosure",
      "/investors/technical-overview",
      "/iso20022",
      "/key-functions",
      "/kob-pos",
      "/kyc-verification",
      "/manual/:type",
      "/monitoring",
      "/njangi",
      "/payment-facilitation",
      "/pending-approval",
      "/personal-accounts",
      "/piggybank",
      "/pricing",
      "/privacy",
      "/products/byo-mobile-money",
      "/profile-settings",
      "/register",
      "/regulatory/aml-cft-pack",
      "/regulatory/business-continuity",
      "/regulatory/cameroon-compliance",
      "/regulatory/corporate-structure",
      "/regulatory/data-protection-policy",
      "/regulatory/filing-pack",
      "/regulatory/internal-control-policy",
      "/regulatory/kyc-due-diligence",
      "/regulatory/license-application",
      "/regulatory/readiness",
      "/regulatory/reporting-templates",
      "/regulatory/risk-assessment",
      "/regulatory/technical-disclosure",
      "/remittance",
      "/rent-reporting",
      "/roi-calculator",
      "/sandbox/simulation-tools",
      "/security-policy",
      "/security/incident-response",
      "/sla",
      "/solutions/credit-scoring",
      "/solutions/fintech-developers",
      "/solutions/mobile-money-integration",
      "/status",
      "/swift",
      "/terms",
      "/tpp-registration",
      "/woo-for-kang"
    ],
    "Public": [
      "*",
      "/app",
      "/app/:institutionId",
      "/app/:institutionId/*",
      "/app/auth",
      "/app/onboarding",
      "/app/register",
      "/app/reset-password",
      "/auth",
      "/bank-dashboard",
      "/bank-dashboard/*",
      "/bank/:institutionId",
      "/bank/:institutionId/apply",
      "/bank/:institutionId/auth",
      "/bank/:institutionId/reset-password",
      "/banking-app/*",
      "/biz",
      "/biz/auth",
      "/biz/register",
      "/biz/reset-password",
      "/communications",
      "/compliance-dashboard",
      "/crediq",
      "/crediq/info",
      "/dashboard",
      "/developer-old",
      "/embed-status-widget",
      "/fee-management",
      "/merchant-register",
      "/pay/:slug",
      "/pay/authorize",
      "/pay/m/:slug",
      "/reset-password",
      "/setup-pin",
      "/staff-login",
      "/status-widget",
      "/store/:merchantId",
      "/support",
      "/support-agent",
      "/support-chat",
      "/system-monitoring",
      "/unsubscribe",
      "/widgets/bank-connect",
      "/widgets/payment",
      "/widgets/verify",
      "access-policy",
      "access-roles",
      "accounts",
      "activity",
      "advanced-analytics",
      "ai-integration-guide",
      "alerts",
      "analytics",
      "anomaly-detection",
      "api-clients",
      "api-directory-submissions",
      "api-docs",
      "api-explorer",
      "api-explorer-static",
      "api-gateway",
      "api-health",
      "api-key-management",
      "api-keys",
      "api-performance",
      "api-playground",
      "api-reference",
      "api-reference/errors",
      "api-reference/http-caching",
      "api-reference/idempotency",
      "api-reference/obie-migration",
      "api-reference/pagination",
      "api-reference/rate-limits",
      "api-reference/token-lifecycle",
      "api-reference/versioning",
      "api-reference/webhook-retry",
      "api-testing",
      "api/aisp",
      "api/banking",
      "api/beneficiaries",
      "api/certificates",
      "api/countries",
      "api/currencies",
      "api/disputes",
      "api/error-codes",
      "api/exports",
      "api/idempotency",
      "api/mobile-money",
      "api/pisp",
      "api/rate-limits",
      "api/refunds",
      "api/risk-audit",
      "api/settlements",
      "api/testing",
      "api/transfers",
      "api/webhooks",
      "approvals",
      "audit",
      "audit-logs",
      "audit-trail",
      "auth-branding",
      "auth/api-keys",
      "authentication",
      "authentication/api-keys",
      "authentication/fapi",
      "authentication/mtls",
      "authentication/oauth2",
      "authorize-payment/:intentId",
      "bank",
      "bank-directory",
      "bank-onboarding",
      "bank-operations",
      "banking",
      "banking-apps",
      "banking/api-logs",
      "banking/approvals",
      "banking/connector-setup",
      "banking/customers",
      "banking/reports",
      "banking/transfers",
      "beneficiaries",
      "bill-management",
      "billing",
      "bills",
      "bookings",
      "branches",
      "branding",
      "bulk-operations",
      "cards",
      "cart",
      "cash-out",
      "certificates",
      "changelog",
      "communications",
      "compare",
      "compliance",
      "compliance-dashboard",
      "compliance/aml",
      "compliance/fapi",
      "compliance/kyc",
      "connector",
      "connector/audit",
      "connector/batches",
      "connector/guide",
      "connector/health",
      "connector/mappings",
      "connector/onboard",
      "connector/reconciliation",
      "connector/status",
      "connector/templates",
      "connector/uploads",
      "connectors/bank-adapter-framework",
      "connectors/bank-onboarding-flow",
      "connectors/byo-mobile-money",
      "connectors/cemac-bank-catalog",
      "connectors/cemac-bank-integration",
      "connectors/multi-rail-failover",
      "connectors/polling-and-webhooks",
      "connectors/soap-bank-adapter",
      "consent-data",
      "consents",
      "console",
      "counter-booking",
      "coupons",
      "credit",
      "credit-api",
      "credit-management",
      "customer-onboarding",
      "customers",
      "discounts",
      "disputes",
      "docs",
      "docs-diagnostics",
      "docs-health",
      "downloads",
      "email-templates",
      "enterprise",
      "escrow",
      "examples",
      "examples/:slug",
      "examples/real-world",
      "exchange-rates",
      "export-center",
      "fee-management",
      "fees",
      "forum",
      "fraud-detection",
      "fund",
      "fund-account",
      "fund-wallet",
      "funding",
      "gateway-audit",
      "gateway-customers",
      "gateway-merchants",
      "gateway-payment-links",
      "gateway-subaccounts",
      "gateway-subscriptions",
      "gateway/authentication",
      "gateway/charge-events",
      "gateway/charges",
      "gateway/compliance",
      "gateway/disputes",
      "gateway/escrow",
      "gateway/funding",
      "gateway/funding-intents",
      "gateway/instant-payouts",
      "gateway/merchant-wallet",
      "gateway/payment-links",
      "gateway/payouts",
      "gateway/paypal",
      "gateway/quickstart",
      "gateway/reconciliation",
      "gateway/refunds",
      "gateway/settlements",
      "gateway/sla",
      "gateway/split-payments",
      "gateway/subscriptions",
      "gateway/tokenisation",
      "gateway/tokenization",
      "gateway/treasury",
      "gateway/verification",
      "gateway/virtual-accounts",
      "gateway/wallets",
      "gateway/webhooks",
      "gateway/webhooks-v2",
      "getting-started",
      "getting-started-by-type",
      "getting-started/authentication",
      "getting-started/first-call",
      "go-live",
      "guide",
      "guides/authentication",
      "guides/charges",
      "guides/choosing-payment-method",
      "guides/first-api-key",
      "guides/first-charge",
      "guides/go-live",
      "guides/going-live-simple",
      "guides/migrate",
      "guides/mobile",
      "guides/pagination-examples",
      "guides/postman",
      "guides/roles-permissions",
      "guides/sdk-versioning",
      "guides/sdks",
      "guides/sdks/:slug",
      "guides/token-lifecycle",
      "guides/web",
      "guides/webhooks",
      "health",
      "help",
      "history",
      "home",
      "homepage-hero",
      "i18n-coverage",
      "idempotency-playground",
      "identity-guide",
      "incidents",
      "integration-layer",
      "integration-workflow",
      "interbank-payments",
      "inventory",
      "invoice-management",
      "invoices",
      "iso20022",
      "iso20022/messages",
      "kyb",
      "kyb-review-queue",
      "kyc",
      "kyc-verification",
      "ledger",
      "linked-account-requests",
      "linked-accounts",
      "load-testing",
      "loans",
      "locations",
      "loyalty",
      "managed-emails",
      "marketplace",
      "marketplace-moderation",
      "messaging",
      "migrate",
      "mobile-money",
      "mobile-money/mtn",
      "mobile-money/orange",
      "more",
      "more/alerts",
      "more/credit",
      "more/disputes",
      "more/help",
      "more/loans",
      "more/remittances",
      "more/savings",
      "more/savings/new",
      "more/settings",
      "more/support",
      "njangi",
      "notification-history",
      "notifications",
      "onboarding",
      "onboarding-guide",
      "onboarding-management",
      "open-banking",
      "open-banking/aisp",
      "open-banking/consents",
      "open-banking/pay-by-bank",
      "open-banking/pisp",
      "open-banking/standards",
      "openapi",
      "orders",
      "overdraft",
      "pay-by-bank",
      "pay-links",
      "payment-command-center",
      "payment-facilitation",
      "payment-links",
      "payments",
      "payments/bills",
      "payments/mobile-money",
      "payments/qr",
      "payments/receive",
      "payments/send",
      "payments/send-abroad",
      "payouts",
      "piggybank",
      "pin-lockout",
      "plans",
      "platform-status",
      "playground",
      "pos-till",
      "products",
      "products/:id",
      "products/new",
      "profile",
      "qr-code",
      "quick-order",
      "quick-start",
      "quickstart",
      "rate-limits",
      "receive",
      "reconciliation",
      "recurring",
      "redoc",
      "redoc-sandbox",
      "reference",
      "reference/error-codes",
      "reference/idempotency",
      "refunds",
      "register",
      "regulatory",
      "remittance",
      "remittance-bank-confirmations",
      "remittance-outbound",
      "remittance-overview",
      "remittance-partners",
      "remittance-settlements",
      "remittance/corridors-quotes",
      "remittance/create-transfer",
      "remittance/errors",
      "remittance/payin-methods",
      "remittance/payout-methods",
      "remittance/sandbox",
      "remittance/webhooks",
      "remittances",
      "rent-reporting",
      "request",
      "revenue",
      "reviews",
      "rewards",
      "rewards-management",
      "rls-monitoring",
      "roles-permissions",
      "routes",
      "sandbox",
      "sandbox/api",
      "sandbox/console",
      "sandbox/credentials",
      "sandbox/data-generator",
      "sandbox/mobile-money",
      "sandbox/overview",
      "sandbox/payout-simulation",
      "sandbox/simulate-webhooks",
      "sandbox/test-cards",
      "sandbox/usage",
      "sandbox/webhook-tester",
      "sandbox/webhook-testing",
      "sandbox/webhooks",
      "savings",
      "scan",
      "scanner",
      "sdks",
      "seating",
      "security",
      "security-dashboard",
      "security/whitepaper",
      "send-money",
      "seo-crawl-check",
      "services",
      "settings",
      "settlement",
      "settlement-accounts",
      "settlement-approval",
      "settlements",
      "sla",
      "snippets",
      "split-bills",
      "staff",
      "staff-authorizations",
      "staff-roles",
      "standards",
      "status",
      "storefront",
      "stores",
      "stores/:merchantId",
      "subaccounts",
      "subscriptions",
      "support",
      "support-agents",
      "support-chat",
      "support-departments",
      "support-settings",
      "supported-countries",
      "swagger",
      "system-alerts",
      "system-config",
      "system-monitoring",
      "team",
      "tenant-connectors",
      "test-report",
      "till",
      "timetable",
      "tpp-registrations",
      "transactions",
      "transfer",
      "translations",
      "travel",
      "travel-bookings",
      "travel-counter-booking",
      "travel-discounts",
      "travel-guide",
      "travel-management",
      "travel-notifications",
      "travel-routes",
      "travel-scanner",
      "travel-seating",
      "travel-services",
      "travel-staff-roles",
      "travel-timetable",
      "travel/:category",
      "travel/:category/:serviceId",
      "travel/:category/:serviceId/trips/:tripId",
      "travel/history",
      "travel/ticket/:bookingId",
      "trust-score",
      "users",
      "wallet",
      "webhook-deliveries",
      "webhook-logs",
      "webhook-simulator",
      "webhooks",
      "webhooks/deliveries",
      "webhooks/provider-receivers",
      "white-label",
      "widgets",
      "wishlist",
      "withdrawal-policies",
      "woo-sync",
      "woocommerce",
      "woocommerce-plugin"
    ],
    "Dashboard": [
      "/banking-ops",
      "/business-kyb-submission",
      "/crediq/dashboard",
      "/credit-report",
      "/credit-score",
      "/loans",
      "/mobile-money",
      "/notification-history",
      "/notifications",
      "/payments",
      "/personal-dashboard",
      "/profile",
      "/savings",
      "/security",
      "/virtual-cards"
    ],
    "Institution/Bank": [
      "/fi-portal",
      "institution-management",
      "institution-urls",
      "institution-verification"
    ],
    "Merchant": [
      "/merchant",
      "merchant-wallet-oversight",
      "merchants",
      "merchants-pos"
    ],
    "Admin": [
      "/admin"
    ],
    "Business PWA": [
      "/biz",
      "business-app-management",
      "business-kyc",
      "travel"
    ],
    "Customer PWA": [
      "/app",
      "customer-apps"
    ],
    "Developer": [
      "/developer",
      "/developer-tools"
    ],
    "Banking App": [
      "/bank/:institutionId",
      "/bank/:institutionId/kyc"
    ]
  }
}